tests/__init__.py
tests/main.py
tests/test_listing_parser.py
tests/test_vehicle_fetcher.py
koreancar-2.0.2.dist-info/LICENSE
koreancar-2.0.2.dist-info/METADATA
koreancar-2.0.2.dist-info/WHEEL
koreancar-2.0.2.dist-info/entry_points.txt
koreancar-2.0.2.dist-info/top_level.txt
koreancar-2.0.2.dist-info/RECORD
