Metadata-Version: 2.2
Name: koreancar
Version: 2.0.2
Summary: A Python library for fetching vehicle data from Encar.com.
Home-page: https://github.com/markolofsen/koreancar
Author: Unrealos
Author-email: m@unrealos.com
License: MIT
Project-URL: Documentation, https://github.com/markolofsen/koreancar
Project-URL: Source, https://github.com/markolofsen/koreancar
Project-URL: Company, https://unrealos.com
Keywords: koreancar,encar,vehicle-data,API,python-library
Classifier: Development Status :: 4 - Beta
Classifier: Intended Audience :: Developers
Classifier: Topic :: Software Development :: Libraries :: Python Modules
Classifier: License :: OSI Approved :: MIT License
Classifier: Programming Language :: Python :: 3
Classifier: Programming Language :: Python :: 3.7
Classifier: Programming Language :: Python :: 3.8
Classifier: Programming Language :: Python :: 3.9
Classifier: Programming Language :: Python :: 3.10
Classifier: Programming Language :: Python :: 3.11
Requires-Python: >=3.7
License-File: LICENSE
Requires-Dist: requests>=2.25.1
Requires-Dist: urllib3>=1.26.5
Provides-Extra: testing
Requires-Dist: pytest>=6.0; extra == "testing"
Requires-Dist: pytest-cov; extra == "testing"
Requires-Dist: tox; extra == "testing"
